{".class":"MypyFile","_fullname":"github.CodeSecurityConfig","future_import_flags":["annotations"],"is_partial_stub_package":false,"is_stub":false,"names":{".class":"SymbolTable","Any":{".class":"SymbolTableNode","cross_ref":"typing.Any","kind":"Gdef","module_hidden":true,"module_public":false},"Attribute":{".class":"SymbolTableNode","cross_ref":"github.GithubObject.Attribute","kind":"Gdef","module_hidden":true,"module_public":false},"CodeSecurityConfig":{".class":"SymbolTableNode","kind":"Gdef","node":{".class":"TypeInfo","_promote":[],"abstract_attributes":[],"alt_promote":null,"bases":["github.GithubObject.NonCompletableGithubObject"],"dataclass_transform_spec":null,"declared_metaclass":null,"defn":{".class":"ClassDef","fullname":"github.CodeSecurityConfig.CodeSecurityConfig","name":"CodeSecurityConfig","type_vars":[]},"deletable_attributes":[],"deprecated":null,"flags":[],"fullname":"github.CodeSecurityConfig.CodeSecurityConfig","has_param_spec_type":false,"metaclass_type":"abc.ABCMeta","metadata":{},"module_name":"github.CodeSecurityConfig","mro":["github.CodeSecurityConfig.CodeSecurityConfig","github.GithubObject.NonCompletableGithubObject","github.GithubObject.GithubObject","abc.ABC","builtins.object"],"names":{".class":"SymbolTable","__repr__":{".class":"SymbolTableNode","kind":"Mdef","node":{".class":"FuncDef","abstract_status":0,"arg_kinds":[0],"arg_names":[null],"dataclass_transform_spec":null,"deprecated":null,"flags":["is_trivial_self"],"fullname":"github.CodeSecurityConfig.CodeSecurityConfig.__repr__","name":"__repr__","original_first_arg":"self","type":{".class":"CallableType","arg_kinds":[0],"arg_names":[null],"arg_types":["github.CodeSecurityConfig.CodeSecurityConfig"],"fallback":"builtins.function","from_concatenate":false,"implicit":false,"imprecise_arg_kinds":false,"is_bound":false,"is_ellipsis_args":false,"name":"__repr__ of CodeSecurityConfig","ret_type":"builtins.str","type_guard":null,"type_is":null,"unpack_kwargs":false,"variables":[]}}},"_advanced_security":{".class":"SymbolTableNode","implicit":true,"kind":"Mdef","node":{".class":"Var","flags":["explicit_self_type","is_ready","is_inferred"],"fullname":"github.CodeSecurityConfig.CodeSecurityConfig._advanced_security","name":"_advanced_security","setter_type":null,"type":{".class":"Instance","args":["builtins.str"],"extra_attrs":null,"type_ref":"github.GithubObject.Attribute"}}},"_code_scanning_default_setup":{".class":"SymbolTableNode","implicit":true,"kind":"Mdef","node":{".class":"Var","flags":["explicit_self_type","is_ready","is_inferred"],"fullname":"github.CodeSecurityConfig.CodeSecurityConfig._code_scanning_default_setup","name":"_code_scanning_default_setup","setter_type":null,"type":{".class":"Instance","args":["builtins.str"],"extra_attrs":null,"type_ref":"github.GithubObject.Attribute"}}},"_code_scanning_delegated_alert_dismissal":{".class":"SymbolTableNode","implicit":true,"kind":"Mdef","node":{".class":"Var","flags":["explicit_self_type","is_ready","is_inferred"],"fullname":"github.CodeSecurityConfig.CodeSecurityConfig._code_scanning_delegated_alert_dismissal","name":"_code_scanning_delegated_alert_dismissal","setter_type":null,"type":{".class":"Instance","args":["builtins.str"],"extra_attrs":null,"type_ref":"github.GithubObject.Attribute"}}},"_created_at":{".class":"SymbolTableNode","implicit":true,"kind":"Mdef","node":{".class":"Var","flags":["explicit_self_type","is_ready","is_inferred"],"fullname":"github.CodeSecurityConfig.CodeSecurityConfig._created_at","name":"_created_at","setter_type":null,"type":{".class":"Instance","args":["datetime.datetime"],"extra_attrs":null,"type_ref":"github.GithubObject.Attribute"}}},"_dependabot_alerts":{".class":"SymbolTableNode","implicit":true,"kind":"Mdef","node":{".class":"Var","flags":["explicit_self_type","is_ready","is_inferred"],"fullname":"github.CodeSecurityConfig.CodeSecurityConfig._dependabot_alerts","name":"_dependabot_alerts","setter_type":null,"type":{".class":"Instance","args":["builtins.str"],"extra_attrs":null,"type_ref":"github.GithubObject.Attribute"}}},"_dependabot_security_updates":{".class":"SymbolTableNode","implicit":true,"kind":"Mdef","node":{".class":"Var","flags":["explicit_self_type","is_ready","is_inferred"],"fullname":"github.CodeSecurityConfig.CodeSecurityConfig._dependabot_security_updates","name":"_dependabot_security_updates","setter_type":null,"type":{".class":"Instance","args":["builtins.str"],"extra_attrs":null,"type_ref":"github.GithubObject.Attribute"}}},"_dependency_graph":{".class":"SymbolTableNode","implicit":true,"kind":"Mdef","node":{".class":"Var","flags":["explicit_self_type","is_ready","is_inferred"],"fullname":"github.CodeSecurityConfig.CodeSecurityConfig._dependency_graph","name":"_dependency_graph","setter_type":null,"type":{".class":"Instance","args":["builtins.str"],"extra_attrs":null,"type_ref":"github.GithubObject.Attribute"}}},"_dependency_graph_autosubmit_action":{".class":"SymbolTableNode","implicit":true,"kind":"Mdef","node":{".class":"Var","flags":["explicit_self_type","is_ready","is_inferred"],"fullname":"github.CodeSecurityConfig.CodeSecurityConfig._dependency_graph_autosubmit_action","name":"_dependency_graph_autosubmit_action","setter_type":null,"type":{".class":"Instance","args":["builtins.str"],"extra_attrs":null,"type_ref":"github.GithubObject.Attribute"}}},"_dependency_graph_autosubmit_action_options":{".class":"SymbolTableNode","implicit":true,"kind":"Mdef","node":{".class":"Var","flags":["explicit_self_type","is_ready","is_inferred"],"fullname":"github.CodeSecurityConfig.CodeSecurityConfig._dependency_graph_autosubmit_action_options","name":"_dependency_graph_autosubmit_action_options","setter_type":null,"type":{".class":"Instance","args":[{".class":"Instance","args":["builtins.str",{".class":"AnyType","missing_import_name":null,"source_any":null,"type_of_any":2}],"extra_attrs":null,"type_ref":"builtins.dict"}],"extra_attrs":null,"type_ref":"github.GithubObject.Attribute"}}},"_description":{".class":"SymbolTableNode","implicit":true,"kind":"Mdef","node":{".class":"Var","flags":["explicit_self_type","is_ready","is_inferred"],"fullname":"github.CodeSecurityConfig.CodeSecurityConfig._description","name":"_description","setter_type":null,"type":{".class":"Instance","args":["builtins.str"],"extra_attrs":null,"type_ref":"github.GithubObject.Attribute"}}},"_enforcement":{".class":"SymbolTableNode","implicit":true,"kind":"Mdef","node":{".class":"Var","flags":["explicit_self_type","is_ready","is_inferred"],"fullname":"github.CodeSecurityConfig.CodeSecurityConfig._enforcement","name":"_enforcement","setter_type":null,"type":{".class":"Instance","args":["builtins.str"],"extra_attrs":null,"type_ref":"github.GithubObject.Attribute"}}},"_html_url":{".class":"SymbolTableNode","implicit":true,"kind":"Mdef","node":{".class":"Var","flags":["explicit_self_type","is_ready","is_inferred"],"fullname":"github.CodeSecurityConfig.CodeSecurityConfig._html_url","name":"_html_url","setter_type":null,"type":{".class":"Instance","args":["builtins.str"],"extra_attrs":null,"type_ref":"github.GithubObject.Attribute"}}},"_id":{".class":"SymbolTableNode","implicit":true,"kind":"Mdef","node":{".class":"Var","flags":["explicit_self_type","is_ready","is_inferred"],"fullname":"github.CodeSecurityConfig.CodeSecurityConfig._id","name":"_id","setter_type":null,"type":{".class":"Instance","args":["builtins.int"],"extra_attrs":null,"type_ref":"github.GithubObject.Attribute"}}},"_initAttributes":{".class":"SymbolTableNode","kind":"Mdef","node":{".class":"FuncDef","abstract_status":0,"arg_kinds":[0],"arg_names":["self"],"dataclass_transform_spec":null,"deprecated":null,"flags":["is_trivial_self"],"fullname":"github.CodeSecurityConfig.CodeSecurityConfig._initAttributes","name":"_initAttributes","original_first_arg":"self","type":{".class":"CallableType","arg_kinds":[0],"arg_names":["self"],"arg_types":["github.CodeSecurityConfig.CodeSecurityConfig"],"fallback":"builtins.function","from_concatenate":false,"implicit":false,"imprecise_arg_kinds":false,"is_bound":false,"is_ellipsis_args":false,"name":"_initAttributes of CodeSecurityConfig","ret_type":{".class":"NoneType"},"type_guard":null,"type_is":null,"unpack_kwargs":false,"variables":[]}}},"_name":{".class":"SymbolTableNode","implicit":true,"kind":"Mdef","node":{".class":"Var","flags":["explicit_self_type","is_ready","is_inferred"],"fullname":"github.CodeSecurityConfig.CodeSecurityConfig._name","name":"_name","setter_type":null,"type":{".class":"Instance","args":["builtins.str"],"extra_attrs":null,"type_ref":"github.GithubObject.Attribute"}}},"_private_vulnerability_reporting":{".class":"SymbolTableNode","implicit":true,"kind":"Mdef","node":{".class":"Var","flags":["explicit_self_type","is_ready","is_inferred"],"fullname":"github.CodeSecurityConfig.CodeSecurityConfig._private_vulnerability_reporting","name":"_private_vulnerability_reporting","setter_type":null,"type":{".class":"Instance","args":["builtins.str"],"extra_attrs":null,"type_ref":"github.GithubObject.Attribute"}}},"_secret_scanning":{".class":"SymbolTableNode","implicit":true,"kind":"Mdef","node":{".class":"Var","flags":["explicit_self_type","is_ready","is_inferred"],"fullname":"github.CodeSecurityConfig.CodeSecurityConfig._secret_scanning","name":"_secret_scanning","setter_type":null,"type":{".class":"Instance","args":["builtins.str"],"extra_attrs":null,"type_ref":"github.GithubObject.Attribute"}}},"_secret_scanning_delegated_alert_dismissal":{".class":"SymbolTableNode","implicit":true,"kind":"Mdef","node":{".class":"Var","flags":["explicit_self_type","is_ready","is_inferred"],"fullname":"github.CodeSecurityConfig.CodeSecurityConfig._secret_scanning_delegated_alert_dismissal","name":"_secret_scanning_delegated_alert_dismissal","setter_type":null,"type":{".class":"Instance","args":["builtins.str"],"extra_attrs":null,"type_ref":"github.GithubObject.Attribute"}}},"_secret_scanning_delegated_bypass":{".class":"SymbolTableNode","implicit":true,"kind":"Mdef","node":{".class":"Var","flags":["explicit_self_type","is_ready","is_inferred"],"fullname":"github.CodeSecurityConfig.CodeSecurityConfig._secret_scanning_delegated_bypass","name":"_secret_scanning_delegated_bypass","setter_type":null,"type":{".class":"Instance","args":["builtins.str"],"extra_attrs":null,"type_ref":"github.GithubObject.Attribute"}}},"_secret_scanning_delegated_bypass_options":{".class":"SymbolTableNode","implicit":true,"kind":"Mdef","node":{".class":"Var","flags":["explicit_self_type","is_ready","is_inferred"],"fullname":"github.CodeSecurityConfig.CodeSecurityConfig._secret_scanning_delegated_bypass_options","name":"_secret_scanning_delegated_bypass_options","setter_type":null,"type":{".class":"Instance","args":[{".class":"Instance","args":["builtins.str",{".class":"AnyType","missing_import_name":null,"source_any":null,"type_of_any":2}],"extra_attrs":null,"type_ref":"builtins.dict"}],"extra_attrs":null,"type_ref":"github.GithubObject.Attribute"}}},"_secret_scanning_generic_secrets":{".class":"SymbolTableNode","implicit":true,"kind":"Mdef","node":{".class":"Var","flags":["explicit_self_type","is_ready","is_inferred"],"fullname":"github.CodeSecurityConfig.CodeSecurityConfig._secret_scanning_generic_secrets","name":"_secret_scanning_generic_secrets","setter_type":null,"type":{".class":"Instance","args":["builtins.str"],"extra_attrs":null,"type_ref":"github.GithubObject.Attribute"}}},"_secret_scanning_non_provider_patterns":{".class":"SymbolTableNode","implicit":true,"kind":"Mdef","node":{".class":"Var","flags":["explicit_self_type","is_ready","is_inferred"],"fullname":"github.CodeSecurityConfig.CodeSecurityConfig._secret_scanning_non_provider_patterns","name":"_secret_scanning_non_provider_patterns","setter_type":null,"type":{".class":"Instance","args":["builtins.str"],"extra_attrs":null,"type_ref":"github.GithubObject.Attribute"}}},"_secret_scanning_push_protection":{".class":"SymbolTableNode","implicit":true,"kind":"Mdef","node":{".class":"Var","flags":["explicit_self_type","is_ready","is_inferred"],"fullname":"github.CodeSecurityConfig.CodeSecurityConfig._secret_scanning_push_protection","name":"_secret_scanning_push_protection","setter_type":null,"type":{".class":"Instance","args":["builtins.str"],"extra_attrs":null,"type_ref":"github.GithubObject.Attribute"}}},"_secret_scanning_validity_checks":{".class":"SymbolTableNode","implicit":true,"kind":"Mdef","node":{".class":"Var","flags":["explicit_self_type","is_ready","is_inferred"],"fullname":"github.CodeSecurityConfig.CodeSecurityConfig._secret_scanning_validity_checks","name":"_secret_scanning_validity_checks","setter_type":null,"type":{".class":"Instance","args":["builtins.str"],"extra_attrs":null,"type_ref":"github.GithubObject.Attribute"}}},"_target_type":{".class":"SymbolTableNode","implicit":true,"kind":"Mdef","node":{".class":"Var","flags":["explicit_self_type","is_ready","is_inferred"],"fullname":"github.CodeSecurityConfig.CodeSecurityConfig._target_type","name":"_target_type","setter_type":null,"type":{".class":"Instance","args":["builtins.str"],"extra_attrs":null,"type_ref":"github.GithubObject.Attribute"}}},"_updated_at":{".class":"SymbolTableNode","implicit":true,"kind":"Mdef","node":{".class":"Var","flags":["explicit_self_type","is_ready","is_inferred"],"fullname":"github.CodeSecurityConfig.CodeSecurityConfig._updated_at","name":"_updated_at","setter_type":null,"type":{".class":"Instance","args":["datetime.datetime"],"extra_attrs":null,"type_ref":"github.GithubObject.Attribute"}}},"_url":{".class":"SymbolTableNode","implicit":true,"kind":"Mdef","node":{".class":"Var","flags":["explicit_self_type","is_ready","is_inferred"],"fullname":"github.CodeSecurityConfig.CodeSecurityConfig._url","name":"_url","setter_type":null,"type":{".class":"Instance","args":["builtins.str"],"extra_attrs":null,"type_ref":"github.GithubObject.Attribute"}}},"_useAttributes":{".class":"SymbolTableNode","kind":"Mdef","node":{".class":"FuncDef","abstract_status":0,"arg_kinds":[0,0],"arg_names":["self","attributes"],"dataclass_transform_spec":null,"deprecated":null,"flags":["is_trivial_self"],"fullname":"github.CodeSecurityConfig.CodeSecurityConfig._useAttributes","name":"_useAttributes","original_first_arg":"self","type":{".class":"CallableType","arg_kinds":[0,0],"arg_names":["self","attributes"],"arg_types":["github.CodeSecurityConfig.CodeSecurityConfig",{".class":"Instance","args":["builtins.str",{".class":"AnyType","missing_import_name":null,"source_any":null,"type_of_any":2}],"extra_attrs":null,"type_ref":"builtins.dict"}],"fallback":"builtins.function","from_concatenate":false,"implicit":false,"imprecise_arg_kinds":false,"is_bound":false,"is_ellipsis_args":false,"name":"_useAttributes of CodeSecurityConfig","ret_type":{".class":"NoneType"},"type_guard":null,"type_is":null,"unpack_kwargs":false,"variables":[]}}},"advanced_security":{".class":"SymbolTableNode","kind":"Mdef","node":{".class":"Decorator","func":{".class":"FuncDef","abstract_status":0,"arg_kinds":[0],"arg_names":["self"],"dataclass_transform_spec":null,"deprecated":null,"flags":["is_property","is_decorated","is_trivial_self"],"fullname":"github.CodeSecurityConfig.CodeSecurityConfig.advanced_security","name":"advanced_security","original_first_arg":"self","type":{".class":"CallableType","arg_kinds":[0],"arg_names":["self"],"arg_types":["github.CodeSecurityConfig.CodeSecurityConfig"],"fallback":"builtins.function","from_concatenate":false,"implicit":false,"imprecise_arg_kinds":false,"is_bound":false,"is_ellipsis_args":false,"name":"advanced_security of CodeSecurityConfig","ret_type":"builtins.str","type_guard":null,"type_is":null,"unpack_kwargs":false,"variables":[]}},"is_overload":false,"var":{".class":"Var","flags":["is_initialized_in_class","is_property","is_ready","is_inferred"],"fullname":"github.CodeSecurityConfig.CodeSecurityConfig.advanced_security","name":"advanced_security","setter_type":null,"type":{".class":"CallableType","arg_kinds":[0],"arg_names":["self"],"arg_types":["github.CodeSecurityConfig.CodeSecurityConfig"],"fallback":"builtins.function","from_concatenate":false,"implicit":false,"imprecise_arg_kinds":false,"is_bound":false,"is_ellipsis_args":false,"name":"advanced_security of CodeSecurityConfig","ret_type":"builtins.str","type_guard":null,"type_is":null,"unpack_kwargs":false,"variables":[]}}}},"code_scanning_default_setup":{".class":"SymbolTableNode","kind":"Mdef","node":{".class":"Decorator","func":{".class":"FuncDef","abstract_status":0,"arg_kinds":[0],"arg_names":["self"],"dataclass_transform_spec":null,"deprecated":null,"flags":["is_property","is_decorated","is_trivial_self"],"fullname":"github.CodeSecurityConfig.CodeSecurityConfig.code_scanning_default_setup","name":"code_scanning_default_setup","original_first_arg":"self","type":{".class":"CallableType","arg_kinds":[0],"arg_names":["self"],"arg_types":["github.CodeSecurityConfig.CodeSecurityConfig"],"fallback":"builtins.function","from_concatenate":false,"implicit":false,"imprecise_arg_kinds":false,"is_bound":false,"is_ellipsis_args":false,"name":"code_scanning_default_setup of CodeSecurityConfig","ret_type":"builtins.str","type_guard":null,"type_is":null,"unpack_kwargs":false,"variables":[]}},"is_overload":false,"var":{".class":"Var","flags":["is_initialized_in_class","is_property","is_ready","is_inferred"],"fullname":"github.CodeSecurityConfig.CodeSecurityConfig.code_scanning_default_setup","name":"code_scanning_default_setup","setter_type":null,"type":{".class":"CallableType","arg_kinds":[0],"arg_names":["self"],"arg_types":["github.CodeSecurityConfig.CodeSecurityConfig"],"fallback":"builtins.function","from_concatenate":false,"implicit":false,"imprecise_arg_kinds":false,"is_bound":false,"is_ellipsis_args":false,"name":"code_scanning_default_setup of CodeSecurityConfig","ret_type":"builtins.str","type_guard":null,"type_is":null,"unpack_kwargs":false,"variables":[]}}}},"code_scanning_delegated_alert_dismissal":{".class":"SymbolTableNode","kind":"Mdef","node":{".class":"Decorator","func":{".class":"FuncDef","abstract_status":0,"arg_kinds":[0],"arg_names":["self"],"dataclass_transform_spec":null,"deprecated":null,"flags":["is_property","is_decorated","is_trivial_self"],"fullname":"github.CodeSecurityConfig.CodeSecurityConfig.code_scanning_delegated_alert_dismissal","name":"code_scanning_delegated_alert_dismissal","original_first_arg":"self","type":{".class":"CallableType","arg_kinds":[0],"arg_names":["self"],"arg_types":["github.CodeSecurityConfig.CodeSecurityConfig"],"fallback":"builtins.function","from_concatenate":false,"implicit":false,"imprecise_arg_kinds":false,"is_bound":false,"is_ellipsis_args":false,"name":"code_scanning_delegated_alert_dismissal of CodeSecurityConfig","ret_type":"builtins.str","type_guard":null,"type_is":null,"unpack_kwargs":false,"variables":[]}},"is_overload":false,"var":{".class":"Var","flags":["is_initialized_in_class","is_property","is_ready","is_inferred"],"fullname":"github.CodeSecurityConfig.CodeSecurityConfig.code_scanning_delegated_alert_dismissal","name":"code_scanning_delegated_alert_dismissal","setter_type":null,"type":{".class":"CallableType","arg_kinds":[0],"arg_names":["self"],"arg_types":["github.CodeSecurityConfig.CodeSecurityConfig"],"fallback":"builtins.function","from_concatenate":false,"implicit":false,"imprecise_arg_kinds":false,"is_bound":false,"is_ellipsis_args":false,"name":"code_scanning_delegated_alert_dismissal of CodeSecurityConfig","ret_type":"builtins.str","type_guard":null,"type_is":null,"unpack_kwargs":false,"variables":[]}}}},"created_at":{".class":"SymbolTableNode","kind":"Mdef","node":{".class":"Decorator","func":{".class":"FuncDef","abstract_status":0,"arg_kinds":[0],"arg_names":["self"],"dataclass_transform_spec":null,"deprecated":null,"flags":["is_property","is_decorated","is_trivial_self"],"fullname":"github.CodeSecurityConfig.CodeSecurityConfig.created_at","name":"created_at","original_first_arg":"self","type":{".class":"CallableType","arg_kinds":[0],"arg_names":["self"],"arg_types":["github.CodeSecurityConfig.CodeSecurityConfig"],"fallback":"builtins.function","from_concatenate":false,"implicit":false,"imprecise_arg_kinds":false,"is_bound":false,"is_ellipsis_args":false,"name":"created_at of CodeSecurityConfig","ret_type":"datetime.datetime","type_guard":null,"type_is":null,"unpack_kwargs":false,"variables":[]}},"is_overload":false,"var":{".class":"Var","flags":["is_initialized_in_class","is_property","is_ready","is_inferred"],"fullname":"github.CodeSecurityConfig.CodeSecurityConfig.created_at","name":"created_at","setter_type":null,"type":{".class":"CallableType","arg_kinds":[0],"arg_names":["self"],"arg_types":["github.CodeSecurityConfig.CodeSecurityConfig"],"fallback":"builtins.function","from_concatenate":false,"implicit":false,"imprecise_arg_kinds":false,"is_bound":false,"is_ellipsis_args":false,"name":"created_at of CodeSecurityConfig","ret_type":"datetime.datetime","type_guard":null,"type_is":null,"unpack_kwargs":false,"variables":[]}}}},"dependabot_alerts":{".class":"SymbolTableNode","kind":"Mdef","node":{".class":"Decorator","func":{".class":"FuncDef","abstract_status":0,"arg_kinds":[0],"arg_names":["self"],"dataclass_transform_spec":null,"deprecated":null,"flags":["is_property","is_decorated","is_trivial_self"],"fullname":"github.CodeSecurityConfig.CodeSecurityConfig.dependabot_alerts","name":"dependabot_alerts","original_first_arg":"self","type":{".class":"CallableType","arg_kinds":[0],"arg_names":["self"],"arg_types":["github.CodeSecurityConfig.CodeSecurityConfig"],"fallback":"builtins.function","from_concatenate":false,"implicit":false,"imprecise_arg_kinds":false,"is_bound":false,"is_ellipsis_args":false,"name":"dependabot_alerts of CodeSecurityConfig","ret_type":"builtins.str","type_guard":null,"type_is":null,"unpack_kwargs":false,"variables":[]}},"is_overload":false,"var":{".class":"Var","flags":["is_initialized_in_class","is_property","is_ready","is_inferred"],"fullname":"github.CodeSecurityConfig.CodeSecurityConfig.dependabot_alerts","name":"dependabot_alerts","setter_type":null,"type":{".class":"CallableType","arg_kinds":[0],"arg_names":["self"],"arg_types":["github.CodeSecurityConfig.CodeSecurityConfig"],"fallback":"builtins.function","from_concatenate":false,"implicit":false,"imprecise_arg_kinds":false,"is_bound":false,"is_ellipsis_args":false,"name":"dependabot_alerts of CodeSecurityConfig","ret_type":"builtins.str","type_guard":null,"type_is":null,"unpack_kwargs":false,"variables":[]}}}},"dependabot_security_updates":{".class":"SymbolTableNode","kind":"Mdef","node":{".class":"Decorator","func":{".class":"FuncDef","abstract_status":0,"arg_kinds":[0],"arg_names":["self"],"dataclass_transform_spec":null,"deprecated":null,"flags":["is_property","is_decorated","is_trivial_self"],"fullname":"github.CodeSecurityConfig.CodeSecurityConfig.dependabot_security_updates","name":"dependabot_security_updates","original_first_arg":"self","type":{".class":"CallableType","arg_kinds":[0],"arg_names":["self"],"arg_types":["github.CodeSecurityConfig.CodeSecurityConfig"],"fallback":"builtins.function","from_concatenate":false,"implicit":false,"imprecise_arg_kinds":false,"is_bound":false,"is_ellipsis_args":false,"name":"dependabot_security_updates of CodeSecurityConfig","ret_type":"builtins.str","type_guard":null,"type_is":null,"unpack_kwargs":false,"variables":[]}},"is_overload":false,"var":{".class":"Var","flags":["is_initialized_in_class","is_property","is_ready","is_inferred"],"fullname":"github.CodeSecurityConfig.CodeSecurityConfig.dependabot_security_updates","name":"dependabot_security_updates","setter_type":null,"type":{".class":"CallableType","arg_kinds":[0],"arg_names":["self"],"arg_types":["github.CodeSecurityConfig.CodeSecurityConfig"],"fallback":"builtins.function","from_concatenate":false,"implicit":false,"imprecise_arg_kinds":false,"is_bound":false,"is_ellipsis_args":false,"name":"dependabot_security_updates of CodeSecurityConfig","ret_type":"builtins.str","type_guard":null,"type_is":null,"unpack_kwargs":false,"variables":[]}}}},"dependency_graph":{".class":"SymbolTableNode","kind":"Mdef","node":{".class":"Decorator","func":{".class":"FuncDef","abstract_status":0,"arg_kinds":[0],"arg_names":["self"],"dataclass_transform_spec":null,"deprecated":null,"flags":["is_property","is_decorated","is_trivial_self"],"fullname":"github.CodeSecurityConfig.CodeSecurityConfig.dependency_graph","name":"dependency_graph","original_first_arg":"self","type":{".class":"CallableType","arg_kinds":[0],"arg_names":["self"],"arg_types":["github.CodeSecurityConfig.CodeSecurityConfig"],"fallback":"builtins.function","from_concatenate":false,"implicit":false,"imprecise_arg_kinds":false,"is_bound":false,"is_ellipsis_args":false,"name":"dependency_graph of CodeSecurityConfig","ret_type":"builtins.str","type_guard":null,"type_is":null,"unpack_kwargs":false,"variables":[]}},"is_overload":false,"var":{".class":"Var","flags":["is_initialized_in_class","is_property","is_ready","is_inferred"],"fullname":"github.CodeSecurityConfig.CodeSecurityConfig.dependency_graph","name":"dependency_graph","setter_type":null,"type":{".class":"CallableType","arg_kinds":[0],"arg_names":["self"],"arg_types":["github.CodeSecurityConfig.CodeSecurityConfig"],"fallback":"builtins.function","from_concatenate":false,"implicit":false,"imprecise_arg_kinds":false,"is_bound":false,"is_ellipsis_args":false,"name":"dependency_graph of CodeSecurityConfig","ret_type":"builtins.str","type_guard":null,"type_is":null,"unpack_kwargs":false,"variables":[]}}}},"dependency_graph_autosubmit_action":{".class":"SymbolTableNode","kind":"Mdef","node":{".class":"Decorator","func":{".class":"FuncDef","abstract_status":0,"arg_kinds":[0],"arg_names":["self"],"dataclass_transform_spec":null,"deprecated":null,"flags":["is_property","is_decorated","is_trivial_self"],"fullname":"github.CodeSecurityConfig.CodeSecurityConfig.dependency_graph_autosubmit_action","name":"dependency_graph_autosubmit_action","original_first_arg":"self","type":{".class":"CallableType","arg_kinds":[0],"arg_names":["self"],"arg_types":["github.CodeSecurityConfig.CodeSecurityConfig"],"fallback":"builtins.function","from_concatenate":false,"implicit":false,"imprecise_arg_kinds":false,"is_bound":false,"is_ellipsis_args":false,"name":"dependency_graph_autosubmit_action of CodeSecurityConfig","ret_type":"builtins.str","type_guard":null,"type_is":null,"unpack_kwargs":false,"variables":[]}},"is_overload":false,"var":{".class":"Var","flags":["is_initialized_in_class","is_property","is_ready","is_inferred"],"fullname":"github.CodeSecurityConfig.CodeSecurityConfig.dependency_graph_autosubmit_action","name":"dependency_graph_autosubmit_action","setter_type":null,"type":{".class":"CallableType","arg_kinds":[0],"arg_names":["self"],"arg_types":["github.CodeSecurityConfig.CodeSecurityConfig"],"fallback":"builtins.function","from_concatenate":false,"implicit":false,"imprecise_arg_kinds":false,"is_bound":false,"is_ellipsis_args":false,"name":"dependency_graph_autosubmit_action of CodeSecurityConfig","ret_type":"builtins.str","type_guard":null,"type_is":null,"unpack_kwargs":false,"variables":[]}}}},"dependency_graph_autosubmit_action_options":{".class":"SymbolTableNode","kind":"Mdef","node":{".class":"Decorator","func":{".class":"FuncDef","abstract_status":0,"arg_kinds":[0],"arg_names":["self"],"dataclass_transform_spec":null,"deprecated":null,"flags":["is_property","is_decorated","is_trivial_self"],"fullname":"github.CodeSecurityConfig.CodeSecurityConfig.dependency_graph_autosubmit_action_options","name":"dependency_graph_autosubmit_action_options","original_first_arg":"self","type":{".class":"CallableType","arg_kinds":[0],"arg_names":["self"],"arg_types":["github.CodeSecurityConfig.CodeSecurityConfig"],"fallback":"builtins.function","from_concatenate":false,"implicit":false,"imprecise_arg_kinds":false,"is_bound":false,"is_ellipsis_args":false,"name":"dependency_graph_autosubmit_action_options of CodeSecurityConfig","ret_type":{".class":"Instance","args":["builtins.str",{".class":"AnyType","missing_import_name":null,"source_any":null,"type_of_any":2}],"extra_attrs":null,"type_ref":"builtins.dict"},"type_guard":null,"type_is":null,"unpack_kwargs":false,"variables":[]}},"is_overload":false,"var":{".class":"Var","flags":["is_initialized_in_class","is_property","is_ready","is_inferred"],"fullname":"github.CodeSecurityConfig.CodeSecurityConfig.dependency_graph_autosubmit_action_options","name":"dependency_graph_autosubmit_action_options","setter_type":null,"type":{".class":"CallableType","arg_kinds":[0],"arg_names":["self"],"arg_types":["github.CodeSecurityConfig.CodeSecurityConfig"],"fallback":"builtins.function","from_concatenate":false,"implicit":false,"imprecise_arg_kinds":false,"is_bound":false,"is_ellipsis_args":false,"name":"dependency_graph_autosubmit_action_options of CodeSecurityConfig","ret_type":{".class":"Instance","args":["builtins.str",{".class":"AnyType","missing_import_name":null,"source_any":null,"type_of_any":2}],"extra_attrs":null,"type_ref":"builtins.dict"},"type_guard":null,"type_is":null,"unpack_kwargs":false,"variables":[]}}}},"description":{".class":"SymbolTableNode","kind":"Mdef","node":{".class":"Decorator","func":{".class":"FuncDef","abstract_status":0,"arg_kinds":[0],"arg_names":["self"],"dataclass_transform_spec":null,"deprecated":null,"flags":["is_property","is_decorated","is_trivial_self"],"fullname":"github.CodeSecurityConfig.CodeSecurityConfig.description","name":"description","original_first_arg":"self","type":{".class":"CallableType","arg_kinds":[0],"arg_names":["self"],"arg_types":["github.CodeSecurityConfig.CodeSecurityConfig"],"fallback":"builtins.function","from_concatenate":false,"implicit":false,"imprecise_arg_kinds":false,"is_bound":false,"is_ellipsis_args":false,"name":"description of CodeSecurityConfig","ret_type":"builtins.str","type_guard":null,"type_is":null,"unpack_kwargs":false,"variables":[]}},"is_overload":false,"var":{".class":"Var","flags":["is_initialized_in_class","is_property","is_ready","is_inferred"],"fullname":"github.CodeSecurityConfig.CodeSecurityConfig.description","name":"description","setter_type":null,"type":{".class":"CallableType","arg_kinds":[0],"arg_names":["self"],"arg_types":["github.CodeSecurityConfig.CodeSecurityConfig"],"fallback":"builtins.function","from_concatenate":false,"implicit":false,"imprecise_arg_kinds":false,"is_bound":false,"is_ellipsis_args":false,"name":"description of CodeSecurityConfig","ret_type":"builtins.str","type_guard":null,"type_is":null,"unpack_kwargs":false,"variables":[]}}}},"enforcement":{".class":"SymbolTableNode","kind":"Mdef","node":{".class":"Decorator","func":{".class":"FuncDef","abstract_status":0,"arg_kinds":[0],"arg_names":["self"],"dataclass_transform_spec":null,"deprecated":null,"flags":["is_property","is_decorated","is_trivial_self"],"fullname":"github.CodeSecurityConfig.CodeSecurityConfig.enforcement","name":"enforcement","original_first_arg":"self","type":{".class":"CallableType","arg_kinds":[0],"arg_names":["self"],"arg_types":["github.CodeSecurityConfig.CodeSecurityConfig"],"fallback":"builtins.function","from_concatenate":false,"implicit":false,"imprecise_arg_kinds":false,"is_bound":false,"is_ellipsis_args":false,"name":"enforcement of CodeSecurityConfig","ret_type":"builtins.str","type_guard":null,"type_is":null,"unpack_kwargs":false,"variables":[]}},"is_overload":false,"var":{".class":"Var","flags":["is_initialized_in_class","is_property","is_ready","is_inferred"],"fullname":"github.CodeSecurityConfig.CodeSecurityConfig.enforcement","name":"enforcement","setter_type":null,"type":{".class":"CallableType","arg_kinds":[0],"arg_names":["self"],"arg_types":["github.CodeSecurityConfig.CodeSecurityConfig"],"fallback":"builtins.function","from_concatenate":false,"implicit":false,"imprecise_arg_kinds":false,"is_bound":false,"is_ellipsis_args":false,"name":"enforcement of CodeSecurityConfig","ret_type":"builtins.str","type_guard":null,"type_is":null,"unpack_kwargs":false,"variables":[]}}}},"html_url":{".class":"SymbolTableNode","kind":"Mdef","node":{".class":"Decorator","func":{".class":"FuncDef","abstract_status":0,"arg_kinds":[0],"arg_names":["self"],"dataclass_transform_spec":null,"deprecated":null,"flags":["is_property","is_decorated","is_trivial_self"],"fullname":"github.CodeSecurityConfig.CodeSecurityConfig.html_url","name":"html_url","original_first_arg":"self","type":{".class":"CallableType","arg_kinds":[0],"arg_names":["self"],"arg_types":["github.CodeSecurityConfig.CodeSecurityConfig"],"fallback":"builtins.function","from_concatenate":false,"implicit":false,"imprecise_arg_kinds":false,"is_bound":false,"is_ellipsis_args":false,"name":"html_url of CodeSecurityConfig","ret_type":"builtins.str","type_guard":null,"type_is":null,"unpack_kwargs":false,"variables":[]}},"is_overload":false,"var":{".class":"Var","flags":["is_initialized_in_class","is_property","is_ready","is_inferred"],"fullname":"github.CodeSecurityConfig.CodeSecurityConfig.html_url","name":"html_url","setter_type":null,"type":{".class":"CallableType","arg_kinds":[0],"arg_names":["self"],"arg_types":["github.CodeSecurityConfig.CodeSecurityConfig"],"fallback":"builtins.function","from_concatenate":false,"implicit":false,"imprecise_arg_kinds":false,"is_bound":false,"is_ellipsis_args":false,"name":"html_url of CodeSecurityConfig","ret_type":"builtins.str","type_guard":null,"type_is":null,"unpack_kwargs":false,"variables":[]}}}},"id":{".class":"SymbolTableNode","kind":"Mdef","node":{".class":"Decorator","func":{".class":"FuncDef","abstract_status":0,"arg_kinds":[0],"arg_names":["self"],"dataclass_transform_spec":null,"deprecated":null,"flags":["is_property","is_decorated","is_trivial_self"],"fullname":"github.CodeSecurityConfig.CodeSecurityConfig.id","name":"id","original_first_arg":"self","type":{".class":"CallableType","arg_kinds":[0],"arg_names":["self"],"arg_types":["github.CodeSecurityConfig.CodeSecurityConfig"],"fallback":"builtins.function","from_concatenate":false,"implicit":false,"imprecise_arg_kinds":false,"is_bound":false,"is_ellipsis_args":false,"name":"id of CodeSecurityConfig","ret_type":"builtins.int","type_guard":null,"type_is":null,"unpack_kwargs":false,"variables":[]}},"is_overload":false,"var":{".class":"Var","flags":["is_initialized_in_class","is_property","is_ready","is_inferred"],"fullname":"github.CodeSecurityConfig.CodeSecurityConfig.id","name":"id","setter_type":null,"type":{".class":"CallableType","arg_kinds":[0],"arg_names":["self"],"arg_types":["github.CodeSecurityConfig.CodeSecurityConfig"],"fallback":"builtins.function","from_concatenate":false,"implicit":false,"imprecise_arg_kinds":false,"is_bound":false,"is_ellipsis_args":false,"name":"id of CodeSecurityConfig","ret_type":"builtins.int","type_guard":null,"type_is":null,"unpack_kwargs":false,"variables":[]}}}},"name":{".class":"SymbolTableNode","kind":"Mdef","node":{".class":"Decorator","func":{".class":"FuncDef","abstract_status":0,"arg_kinds":[0],"arg_names":["self"],"dataclass_transform_spec":null,"deprecated":null,"flags":["is_property","is_decorated","is_trivial_self"],"fullname":"github.CodeSecurityConfig.CodeSecurityConfig.name","name":"name","original_first_arg":"self","type":{".class":"CallableType","arg_kinds":[0],"arg_names":["self"],"arg_types":["github.CodeSecurityConfig.CodeSecurityConfig"],"fallback":"builtins.function","from_concatenate":false,"implicit":false,"imprecise_arg_kinds":false,"is_bound":false,"is_ellipsis_args":false,"name":"name of CodeSecurityConfig","ret_type":"builtins.str","type_guard":null,"type_is":null,"unpack_kwargs":false,"variables":[]}},"is_overload":false,"var":{".class":"Var","flags":["is_initialized_in_class","is_property","is_ready","is_inferred"],"fullname":"github.CodeSecurityConfig.CodeSecurityConfig.name","name":"name","setter_type":null,"type":{".class":"CallableType","arg_kinds":[0],"arg_names":["self"],"arg_types":["github.CodeSecurityConfig.CodeSecurityConfig"],"fallback":"builtins.function","from_concatenate":false,"implicit":false,"imprecise_arg_kinds":false,"is_bound":false,"is_ellipsis_args":false,"name":"name of CodeSecurityConfig","ret_type":"builtins.str","type_guard":null,"type_is":null,"unpack_kwargs":false,"variables":[]}}}},"private_vulnerability_reporting":{".class":"SymbolTableNode","kind":"Mdef","node":{".class":"Decorator","func":{".class":"FuncDef","abstract_status":0,"arg_kinds":[0],"arg_names":["self"],"dataclass_transform_spec":null,"deprecated":null,"flags":["is_property","is_decorated","is_trivial_self"],"fullname":"github.CodeSecurityConfig.CodeSecurityConfig.private_vulnerability_reporting","name":"private_vulnerability_reporting","original_first_arg":"self","type":{".class":"CallableType","arg_kinds":[0],"arg_names":["self"],"arg_types":["github.CodeSecurityConfig.CodeSecurityConfig"],"fallback":"builtins.function","from_concatenate":false,"implicit":false,"imprecise_arg_kinds":false,"is_bound":false,"is_ellipsis_args":false,"name":"private_vulnerability_reporting of CodeSecurityConfig","ret_type":"builtins.str","type_guard":null,"type_is":null,"unpack_kwargs":false,"variables":[]}},"is_overload":false,"var":{".class":"Var","flags":["is_initialized_in_class","is_property","is_ready","is_inferred"],"fullname":"github.CodeSecurityConfig.CodeSecurityConfig.private_vulnerability_reporting","name":"private_vulnerability_reporting","setter_type":null,"type":{".class":"CallableType","arg_kinds":[0],"arg_names":["self"],"arg_types":["github.CodeSecurityConfig.CodeSecurityConfig"],"fallback":"builtins.function","from_concatenate":false,"implicit":false,"imprecise_arg_kinds":false,"is_bound":false,"is_ellipsis_args":false,"name":"private_vulnerability_reporting of CodeSecurityConfig","ret_type":"builtins.str","type_guard":null,"type_is":null,"unpack_kwargs":false,"variables":[]}}}},"secret_scanning":{".class":"SymbolTableNode","kind":"Mdef","node":{".class":"Decorator","func":{".class":"FuncDef","abstract_status":0,"arg_kinds":[0],"arg_names":["self"],"dataclass_transform_spec":null,"deprecated":null,"flags":["is_property","is_decorated","is_trivial_self"],"fullname":"github.CodeSecurityConfig.CodeSecurityConfig.secret_scanning","name":"secret_scanning","original_first_arg":"self","type":{".class":"CallableType","arg_kinds":[0],"arg_names":["self"],"arg_types":["github.CodeSecurityConfig.CodeSecurityConfig"],"fallback":"builtins.function","from_concatenate":false,"implicit":false,"imprecise_arg_kinds":false,"is_bound":false,"is_ellipsis_args":false,"name":"secret_scanning of CodeSecurityConfig","ret_type":"builtins.str","type_guard":null,"type_is":null,"unpack_kwargs":false,"variables":[]}},"is_overload":false,"var":{".class":"Var","flags":["is_initialized_in_class","is_property","is_ready","is_inferred"],"fullname":"github.CodeSecurityConfig.CodeSecurityConfig.secret_scanning","name":"secret_scanning","setter_type":null,"type":{".class":"CallableType","arg_kinds":[0],"arg_names":["self"],"arg_types":["github.CodeSecurityConfig.CodeSecurityConfig"],"fallback":"builtins.function","from_concatenate":false,"implicit":false,"imprecise_arg_kinds":false,"is_bound":false,"is_ellipsis_args":false,"name":"secret_scanning of CodeSecurityConfig","ret_type":"builtins.str","type_guard":null,"type_is":null,"unpack_kwargs":false,"variables":[]}}}},"secret_scanning_delegated_alert_dismissal":{".class":"SymbolTableNode","kind":"Mdef","node":{".class":"Decorator","func":{".class":"FuncDef","abstract_status":0,"arg_kinds":[0],"arg_names":["self"],"dataclass_transform_spec":null,"deprecated":null,"flags":["is_property","is_decorated","is_trivial_self"],"fullname":"github.CodeSecurityConfig.CodeSecurityConfig.secret_scanning_delegated_alert_dismissal","name":"secret_scanning_delegated_alert_dismissal","original_first_arg":"self","type":{".class":"CallableType","arg_kinds":[0],"arg_names":["self"],"arg_types":["github.CodeSecurityConfig.CodeSecurityConfig"],"fallback":"builtins.function","from_concatenate":false,"implicit":false,"imprecise_arg_kinds":false,"is_bound":false,"is_ellipsis_args":false,"name":"secret_scanning_delegated_alert_dismissal of CodeSecurityConfig","ret_type":"builtins.str","type_guard":null,"type_is":null,"unpack_kwargs":false,"variables":[]}},"is_overload":false,"var":{".class":"Var","flags":["is_initialized_in_class","is_property","is_ready","is_inferred"],"fullname":"github.CodeSecurityConfig.CodeSecurityConfig.secret_scanning_delegated_alert_dismissal","name":"secret_scanning_delegated_alert_dismissal","setter_type":null,"type":{".class":"CallableType","arg_kinds":[0],"arg_names":["self"],"arg_types":["github.CodeSecurityConfig.CodeSecurityConfig"],"fallback":"builtins.function","from_concatenate":false,"implicit":false,"imprecise_arg_kinds":false,"is_bound":false,"is_ellipsis_args":false,"name":"secret_scanning_delegated_alert_dismissal of CodeSecurityConfig","ret_type":"builtins.str","type_guard":null,"type_is":null,"unpack_kwargs":false,"variables":[]}}}},"secret_scanning_delegated_bypass":{".class":"SymbolTableNode","kind":"Mdef","node":{".class":"Decorator","func":{".class":"FuncDef","abstract_status":0,"arg_kinds":[0],"arg_names":["self"],"dataclass_transform_spec":null,"deprecated":null,"flags":["is_property","is_decorated","is_trivial_self"],"fullname":"github.CodeSecurityConfig.CodeSecurityConfig.secret_scanning_delegated_bypass","name":"secret_scanning_delegated_bypass","original_first_arg":"self","type":{".class":"CallableType","arg_kinds":[0],"arg_names":["self"],"arg_types":["github.CodeSecurityConfig.CodeSecurityConfig"],"fallback":"builtins.function","from_concatenate":false,"implicit":false,"imprecise_arg_kinds":false,"is_bound":false,"is_ellipsis_args":false,"name":"secret_scanning_delegated_bypass of CodeSecurityConfig","ret_type":"builtins.str","type_guard":null,"type_is":null,"unpack_kwargs":false,"variables":[]}},"is_overload":false,"var":{".class":"Var","flags":["is_initialized_in_class","is_property","is_ready","is_inferred"],"fullname":"github.CodeSecurityConfig.CodeSecurityConfig.secret_scanning_delegated_bypass","name":"secret_scanning_delegated_bypass","setter_type":null,"type":{".class":"CallableType","arg_kinds":[0],"arg_names":["self"],"arg_types":["github.CodeSecurityConfig.CodeSecurityConfig"],"fallback":"builtins.function","from_concatenate":false,"implicit":false,"imprecise_arg_kinds":false,"is_bound":false,"is_ellipsis_args":false,"name":"secret_scanning_delegated_bypass of CodeSecurityConfig","ret_type":"builtins.str","type_guard":null,"type_is":null,"unpack_kwargs":false,"variables":[]}}}},"secret_scanning_delegated_bypass_options":{".class":"SymbolTableNode","kind":"Mdef","node":{".class":"Decorator","func":{".class":"FuncDef","abstract_status":0,"arg_kinds":[0],"arg_names":["self"],"dataclass_transform_spec":null,"deprecated":null,"flags":["is_property","is_decorated","is_trivial_self"],"fullname":"github.CodeSecurityConfig.CodeSecurityConfig.secret_scanning_delegated_bypass_options","name":"secret_scanning_delegated_bypass_options","original_first_arg":"self","type":{".class":"CallableType","arg_kinds":[0],"arg_names":["self"],"arg_types":["github.CodeSecurityConfig.CodeSecurityConfig"],"fallback":"builtins.function","from_concatenate":false,"implicit":false,"imprecise_arg_kinds":false,"is_bound":false,"is_ellipsis_args":false,"name":"secret_scanning_delegated_bypass_options of CodeSecurityConfig","ret_type":{".class":"Instance","args":["builtins.str",{".class":"AnyType","missing_import_name":null,"source_any":null,"type_of_any":2}],"extra_attrs":null,"type_ref":"builtins.dict"},"type_guard":null,"type_is":null,"unpack_kwargs":false,"variables":[]}},"is_overload":false,"var":{".class":"Var","flags":["is_initialized_in_class","is_property","is_ready","is_inferred"],"fullname":"github.CodeSecurityConfig.CodeSecurityConfig.secret_scanning_delegated_bypass_options","name":"secret_scanning_delegated_bypass_options","setter_type":null,"type":{".class":"CallableType","arg_kinds":[0],"arg_names":["self"],"arg_types":["github.CodeSecurityConfig.CodeSecurityConfig"],"fallback":"builtins.function","from_concatenate":false,"implicit":false,"imprecise_arg_kinds":false,"is_bound":false,"is_ellipsis_args":false,"name":"secret_scanning_delegated_bypass_options of CodeSecurityConfig","ret_type":{".class":"Instance","args":["builtins.str",{".class":"AnyType","missing_import_name":null,"source_any":null,"type_of_any":2}],"extra_attrs":null,"type_ref":"builtins.dict"},"type_guard":null,"type_is":null,"unpack_kwargs":false,"variables":[]}}}},"secret_scanning_generic_secrets":{".class":"SymbolTableNode","kind":"Mdef","node":{".class":"Decorator","func":{".class":"FuncDef","abstract_status":0,"arg_kinds":[0],"arg_names":["self"],"dataclass_transform_spec":null,"deprecated":null,"flags":["is_property","is_decorated","is_trivial_self"],"fullname":"github.CodeSecurityConfig.CodeSecurityConfig.secret_scanning_generic_secrets","name":"secret_scanning_generic_secrets","original_first_arg":"self","type":{".class":"CallableType","arg_kinds":[0],"arg_names":["self"],"arg_types":["github.CodeSecurityConfig.CodeSecurityConfig"],"fallback":"builtins.function","from_concatenate":false,"implicit":false,"imprecise_arg_kinds":false,"is_bound":false,"is_ellipsis_args":false,"name":"secret_scanning_generic_secrets of CodeSecurityConfig","ret_type":"builtins.str","type_guard":null,"type_is":null,"unpack_kwargs":false,"variables":[]}},"is_overload":false,"var":{".class":"Var","flags":["is_initialized_in_class","is_property","is_ready","is_inferred"],"fullname":"github.CodeSecurityConfig.CodeSecurityConfig.secret_scanning_generic_secrets","name":"secret_scanning_generic_secrets","setter_type":null,"type":{".class":"CallableType","arg_kinds":[0],"arg_names":["self"],"arg_types":["github.CodeSecurityConfig.CodeSecurityConfig"],"fallback":"builtins.function","from_concatenate":false,"implicit":false,"imprecise_arg_kinds":false,"is_bound":false,"is_ellipsis_args":false,"name":"secret_scanning_generic_secrets of CodeSecurityConfig","ret_type":"builtins.str","type_guard":null,"type_is":null,"unpack_kwargs":false,"variables":[]}}}},"secret_scanning_non_provider_patterns":{".class":"SymbolTableNode","kind":"Mdef","node":{".class":"Decorator","func":{".class":"FuncDef","abstract_status":0,"arg_kinds":[0],"arg_names":["self"],"dataclass_transform_spec":null,"deprecated":null,"flags":["is_property","is_decorated","is_trivial_self"],"fullname":"github.CodeSecurityConfig.CodeSecurityConfig.secret_scanning_non_provider_patterns","name":"secret_scanning_non_provider_patterns","original_first_arg":"self","type":{".class":"CallableType","arg_kinds":[0],"arg_names":["self"],"arg_types":["github.CodeSecurityConfig.CodeSecurityConfig"],"fallback":"builtins.function","from_concatenate":false,"implicit":false,"imprecise_arg_kinds":false,"is_bound":false,"is_ellipsis_args":false,"name":"secret_scanning_non_provider_patterns of CodeSecurityConfig","ret_type":"builtins.str","type_guard":null,"type_is":null,"unpack_kwargs":false,"variables":[]}},"is_overload":false,"var":{".class":"Var","flags":["is_initialized_in_class","is_property","is_ready","is_inferred"],"fullname":"github.CodeSecurityConfig.CodeSecurityConfig.secret_scanning_non_provider_patterns","name":"secret_scanning_non_provider_patterns","setter_type":null,"type":{".class":"CallableType","arg_kinds":[0],"arg_names":["self"],"arg_types":["github.CodeSecurityConfig.CodeSecurityConfig"],"fallback":"builtins.function","from_concatenate":false,"implicit":false,"imprecise_arg_kinds":false,"is_bound":false,"is_ellipsis_args":false,"name":"secret_scanning_non_provider_patterns of CodeSecurityConfig","ret_type":"builtins.str","type_guard":null,"type_is":null,"unpack_kwargs":false,"variables":[]}}}},"secret_scanning_push_protection":{".class":"SymbolTableNode","kind":"Mdef","node":{".class":"Decorator","func":{".class":"FuncDef","abstract_status":0,"arg_kinds":[0],"arg_names":["self"],"dataclass_transform_spec":null,"deprecated":null,"flags":["is_property","is_decorated","is_trivial_self"],"fullname":"github.CodeSecurityConfig.CodeSecurityConfig.secret_scanning_push_protection","name":"secret_scanning_push_protection","original_first_arg":"self","type":{".class":"CallableType","arg_kinds":[0],"arg_names":["self"],"arg_types":["github.CodeSecurityConfig.CodeSecurityConfig"],"fallback":"builtins.function","from_concatenate":false,"implicit":false,"imprecise_arg_kinds":false,"is_bound":false,"is_ellipsis_args":false,"name":"secret_scanning_push_protection of CodeSecurityConfig","ret_type":"builtins.str","type_guard":null,"type_is":null,"unpack_kwargs":false,"variables":[]}},"is_overload":false,"var":{".class":"Var","flags":["is_initialized_in_class","is_property","is_ready","is_inferred"],"fullname":"github.CodeSecurityConfig.CodeSecurityConfig.secret_scanning_push_protection","name":"secret_scanning_push_protection","setter_type":null,"type":{".class":"CallableType","arg_kinds":[0],"arg_names":["self"],"arg_types":["github.CodeSecurityConfig.CodeSecurityConfig"],"fallback":"builtins.function","from_concatenate":false,"implicit":false,"imprecise_arg_kinds":false,"is_bound":false,"is_ellipsis_args":false,"name":"secret_scanning_push_protection of CodeSecurityConfig","ret_type":"builtins.str","type_guard":null,"type_is":null,"unpack_kwargs":false,"variables":[]}}}},"secret_scanning_validity_checks":{".class":"SymbolTableNode","kind":"Mdef","node":{".class":"Decorator","func":{".class":"FuncDef","abstract_status":0,"arg_kinds":[0],"arg_names":["self"],"dataclass_transform_spec":null,"deprecated":null,"flags":["is_property","is_decorated","is_trivial_self"],"fullname":"github.CodeSecurityConfig.CodeSecurityConfig.secret_scanning_validity_checks","name":"secret_scanning_validity_checks","original_first_arg":"self","type":{".class":"CallableType","arg_kinds":[0],"arg_names":["self"],"arg_types":["github.CodeSecurityConfig.CodeSecurityConfig"],"fallback":"builtins.function","from_concatenate":false,"implicit":false,"imprecise_arg_kinds":false,"is_bound":false,"is_ellipsis_args":false,"name":"secret_scanning_validity_checks of CodeSecurityConfig","ret_type":"builtins.str","type_guard":null,"type_is":null,"unpack_kwargs":false,"variables":[]}},"is_overload":false,"var":{".class":"Var","flags":["is_initialized_in_class","is_property","is_ready","is_inferred"],"fullname":"github.CodeSecurityConfig.CodeSecurityConfig.secret_scanning_validity_checks","name":"secret_scanning_validity_checks","setter_type":null,"type":{".class":"CallableType","arg_kinds":[0],"arg_names":["self"],"arg_types":["github.CodeSecurityConfig.CodeSecurityConfig"],"fallback":"builtins.function","from_concatenate":false,"implicit":false,"imprecise_arg_kinds":false,"is_bound":false,"is_ellipsis_args":false,"name":"secret_scanning_validity_checks of CodeSecurityConfig","ret_type":"builtins.str","type_guard":null,"type_is":null,"unpack_kwargs":false,"variables":[]}}}},"target_type":{".class":"SymbolTableNode","kind":"Mdef","node":{".class":"Decorator","func":{".class":"FuncDef","abstract_status":0,"arg_kinds":[0],"arg_names":["self"],"dataclass_transform_spec":null,"deprecated":null,"flags":["is_property","is_decorated","is_trivial_self"],"fullname":"github.CodeSecurityConfig.CodeSecurityConfig.target_type","name":"target_type","original_first_arg":"self","type":{".class":"CallableType","arg_kinds":[0],"arg_names":["self"],"arg_types":["github.CodeSecurityConfig.CodeSecurityConfig"],"fallback":"builtins.function","from_concatenate":false,"implicit":false,"imprecise_arg_kinds":false,"is_bound":false,"is_ellipsis_args":false,"name":"target_type of CodeSecurityConfig","ret_type":"builtins.str","type_guard":null,"type_is":null,"unpack_kwargs":false,"variables":[]}},"is_overload":false,"var":{".class":"Var","flags":["is_initialized_in_class","is_property","is_ready","is_inferred"],"fullname":"github.CodeSecurityConfig.CodeSecurityConfig.target_type","name":"target_type","setter_type":null,"type":{".class":"CallableType","arg_kinds":[0],"arg_names":["self"],"arg_types":["github.CodeSecurityConfig.CodeSecurityConfig"],"fallback":"builtins.function","from_concatenate":false,"implicit":false,"imprecise_arg_kinds":false,"is_bound":false,"is_ellipsis_args":false,"name":"target_type of CodeSecurityConfig","ret_type":"builtins.str","type_guard":null,"type_is":null,"unpack_kwargs":false,"variables":[]}}}},"updated_at":{".class":"SymbolTableNode","kind":"Mdef","node":{".class":"Decorator","func":{".class":"FuncDef","abstract_status":0,"arg_kinds":[0],"arg_names":["self"],"dataclass_transform_spec":null,"deprecated":null,"flags":["is_property","is_decorated","is_trivial_self"],"fullname":"github.CodeSecurityConfig.CodeSecurityConfig.updated_at","name":"updated_at","original_first_arg":"self","type":{".class":"CallableType","arg_kinds":[0],"arg_names":["self"],"arg_types":["github.CodeSecurityConfig.CodeSecurityConfig"],"fallback":"builtins.function","from_concatenate":false,"implicit":false,"imprecise_arg_kinds":false,"is_bound":false,"is_ellipsis_args":false,"name":"updated_at of CodeSecurityConfig","ret_type":"datetime.datetime","type_guard":null,"type_is":null,"unpack_kwargs":false,"variables":[]}},"is_overload":false,"var":{".class":"Var","flags":["is_initialized_in_class","is_property","is_ready","is_inferred"],"fullname":"github.CodeSecurityConfig.CodeSecurityConfig.updated_at","name":"updated_at","setter_type":null,"type":{".class":"CallableType","arg_kinds":[0],"arg_names":["self"],"arg_types":["github.CodeSecurityConfig.CodeSecurityConfig"],"fallback":"builtins.function","from_concatenate":false,"implicit":false,"imprecise_arg_kinds":false,"is_bound":false,"is_ellipsis_args":false,"name":"updated_at of CodeSecurityConfig","ret_type":"datetime.datetime","type_guard":null,"type_is":null,"unpack_kwargs":false,"variables":[]}}}},"url":{".class":"SymbolTableNode","kind":"Mdef","node":{".class":"Decorator","func":{".class":"FuncDef","abstract_status":0,"arg_kinds":[0],"arg_names":["self"],"dataclass_transform_spec":null,"deprecated":null,"flags":["is_property","is_decorated","is_trivial_self"],"fullname":"github.CodeSecurityConfig.CodeSecurityConfig.url","name":"url","original_first_arg":"self","type":{".class":"CallableType","arg_kinds":[0],"arg_names":["self"],"arg_types":["github.CodeSecurityConfig.CodeSecurityConfig"],"fallback":"builtins.function","from_concatenate":false,"implicit":false,"imprecise_arg_kinds":false,"is_bound":false,"is_ellipsis_args":false,"name":"url of CodeSecurityConfig","ret_type":"builtins.str","type_guard":null,"type_is":null,"unpack_kwargs":false,"variables":[]}},"is_overload":false,"var":{".class":"Var","flags":["is_initialized_in_class","is_property","is_ready","is_inferred"],"fullname":"github.CodeSecurityConfig.CodeSecurityConfig.url","name":"url","setter_type":null,"type":{".class":"CallableType","arg_kinds":[0],"arg_names":["self"],"arg_types":["github.CodeSecurityConfig.CodeSecurityConfig"],"fallback":"builtins.function","from_concatenate":false,"implicit":false,"imprecise_arg_kinds":false,"is_bound":false,"is_ellipsis_args":false,"name":"url of CodeSecurityConfig","ret_type":"builtins.str","type_guard":null,"type_is":null,"unpack_kwargs":false,"variables":[]}}}}},"self_type":{".class":"TypeVarType","default":{".class":"AnyType","missing_import_name":null,"source_any":null,"type_of_any":4},"fullname":"github.CodeSecurityConfig.CodeSecurityConfig.Self","id":0,"name":"Self","namespace":"","upper_bound":"github.CodeSecurityConfig.CodeSecurityConfig","values":[],"variance":0},"slots":null,"tuple_type":null,"type_vars":[],"typeddict_type":null}},"NonCompletableGithubObject":{".class":"SymbolTableNode","cross_ref":"github.GithubObject.NonCompletableGithubObject","kind":"Gdef","module_hidden":true,"module_public":false},"NotSet":{".class":"SymbolTableNode","cross_ref":"github.GithubObject.NotSet","kind":"Gdef","module_hidden":true,"module_public":false},"__annotations__":{".class":"SymbolTableNode","kind":"Gdef","node":{".class":"Var","flags":["is_ready"],"fullname":"github.CodeSecurityConfig.__annotations__","name":"__annotations__","setter_type":null,"type":{".class":"Instance","args":["builtins.str",{".class":"AnyType","missing_import_name":null,"source_any":null,"type_of_any":6}],"extra_attrs":null,"type_ref":"builtins.dict"}}},"__doc__":{".class":"SymbolTableNode","kind":"Gdef","node":{".class":"Var","flags":["is_ready"],"fullname":"github.CodeSecurityConfig.__doc__","name":"__doc__","setter_type":null,"type":"builtins.str"}},"__file__":{".class":"SymbolTableNode","kind":"Gdef","node":{".class":"Var","flags":["is_ready"],"fullname":"github.CodeSecurityConfig.__file__","name":"__file__","setter_type":null,"type":"builtins.str"}},"__name__":{".class":"SymbolTableNode","kind":"Gdef","node":{".class":"Var","flags":["is_ready"],"fullname":"github.CodeSecurityConfig.__name__","name":"__name__","setter_type":null,"type":"builtins.str"}},"__package__":{".class":"SymbolTableNode","kind":"Gdef","node":{".class":"Var","flags":["is_ready"],"fullname":"github.CodeSecurityConfig.__package__","name":"__package__","setter_type":null,"type":"builtins.str"}},"__spec__":{".class":"SymbolTableNode","kind":"Gdef","node":{".class":"Var","flags":["is_ready"],"fullname":"github.CodeSecurityConfig.__spec__","name":"__spec__","setter_type":null,"type":"_frozen_importlib.ModuleSpec"}},"annotations":{".class":"SymbolTableNode","cross_ref":"__future__.annotations","kind":"Gdef","module_hidden":true,"module_public":false},"datetime":{".class":"SymbolTableNode","cross_ref":"datetime.datetime","kind":"Gdef","module_hidden":true,"module_public":false}},"path":"/Users/niccolocalandri/code/ultraWrap/.venv/lib/python3.14/site-packages/github/CodeSecurityConfig.py"}